failure_analysis_toolkit-1.0.1.dist-info/licenses/LICENSE
prob_failure_toolkit/__init__.py
prob_failure_toolkit/formulas/__init__.py
prob_failure_toolkit/formulas/beam.py
prob_failure_toolkit/formulas/gear.py
prob_failure_toolkit/formulas/shaft.py
prob_failure_toolkit/formulas/sheet_metal.py
prob_failure_toolkit/plotting/__init__.py
prob_failure_toolkit/plotting/plot_utils.py
prob_failure_toolkit/statistical_tools/__init__.py
prob_failure_toolkit/statistical_tools/monte_carlo.py
prob_failure_toolkit/statistical_tools/sensitivity.py
failure_analysis_toolkit-1.0.1.dist-info/METADATA
failure_analysis_toolkit-1.0.1.dist-info/WHEEL
failure_analysis_toolkit-1.0.1.dist-info/top_level.txt
failure_analysis_toolkit-1.0.1.dist-info/RECORD
