Metadata-Version: 2.4
Name: failure-analysis-toolkit
Version: 1.0.1
Summary: A toolkit for probabilistic failure analysis of mechanical components
Author-email: Mohnish S <mohnishs2006@gmail.com>
Project-URL: Homepage, https://github.com/SMohnish/prob_failure_toolkit
Project-URL: Bug Tracker, https://github.com/SMohnish/prob_failure_toolkit/issues
Classifier: Programming Language :: Python :: 3
Classifier: License :: OSI Approved :: MIT License
Classifier: Operating System :: OS Independent
Requires-Python: >=3.7
License-File: LICENSE
Requires-Dist: numpy
Requires-Dist: matplotlib
Requires-Dist: scipy
Dynamic: license-file
